interval/__init__.py
interval/_version.py
rms_interval-0.0.6.dist-info/LICENSE
rms_interval-0.0.6.dist-info/METADATA
rms_interval-0.0.6.dist-info/WHEEL
rms_interval-0.0.6.dist-info/top_level.txt
rms_interval-0.0.6.dist-info/RECORD
